precompose_utils/__init__.py
precompose_utils/clean.py
precompose_utils/lockfile.py
precompose_utils/mount.py
precompose_utils/paths.py
precompose_utils/storage.py
precompose_utils/unmount.py
precompose_utils-0.1.2.dist-info/LICENSE.md
precompose_utils-0.1.2.dist-info/METADATA
precompose_utils-0.1.2.dist-info/WHEEL
precompose_utils-0.1.2.dist-info/entry_points.txt
precompose_utils-0.1.2.dist-info/top_level.txt
precompose_utils-0.1.2.dist-info/RECORD
